{
  "Population": {
    "keyword": "Population",
    "fields": [
      {
        "name": "Number",
        "type": "StringType"
      },
      {
        "name": "Year",
        "type": "StringType"
      },
      {
        "name": "Series",
        "type": "StringType"
      },
      {
        "name": "Value",
        "type": "StringType"
      },
      {
        "name": "Footnotes",
        "type": "StringType"
      },
      {
        "name": "Source",
        "type": "StringType"
      }
    ]
  }
}